mcp_bot/__init__.py
mcp_bot/app.py
mcp_bot/main.py
mcp_bot-0.1.1.dist-info/METADATA
mcp_bot-0.1.1.dist-info/WHEEL
mcp_bot-0.1.1.dist-info/entry_points.txt
mcp_bot-0.1.1.dist-info/top_level.txt
mcp_bot-0.1.1.dist-info/RECORD
