Metadata-Version: 2.4
Name: mcp-bot
Version: 0.1.1
Summary: An interactive chat UI for communicating with your MCP Tools via AI Agents.
Home-page: https://github.com/NilavoBoral/mcp-bot
Author: Nilavo Boral
Author-email: nilavoboral@gmail.com
Project-URL: LinkedIn, https://www.linkedin.com/in/nilavo-boral-123bb5228/
Classifier: Programming Language :: Python :: 3.11
Classifier: License :: OSI Approved :: MIT License
Classifier: Operating System :: OS Independent
Classifier: Intended Audience :: Developers
Classifier: Topic :: Software Development :: User Interfaces
Classifier: Topic :: Scientific/Engineering :: Artificial Intelligence
Requires-Python: >=3.11
Requires-Dist: streamlit==1.49.1
Requires-Dist: langchain==1.0.5
Requires-Dist: langchain-core==1.0.4
Requires-Dist: langchain-google-genai==3.0.1
Requires-Dist: langchain-mcp-adapters==0.1.12
Requires-Dist: nest_asyncio==1.6.0
Dynamic: author
Dynamic: author-email
Dynamic: classifier
Dynamic: description
Dynamic: description-content-type
Dynamic: home-page
Dynamic: project-url
Dynamic: requires-dist
Dynamic: requires-python
Dynamic: summary
